proxmin/__init__.py
proxmin/algorithms.py
proxmin/nmf.py
proxmin/operators.py
proxmin/utils.py
proxmin-0.6.12.dist-info/LICENSE.md
proxmin-0.6.12.dist-info/METADATA
proxmin-0.6.12.dist-info/WHEEL
proxmin-0.6.12.dist-info/top_level.txt
proxmin-0.6.12.dist-info/RECORD
