Metadata-Version: 2.1
Name: proxmin
Version: 0.6.12
Summary: Proximal methods for constrained optimization
Home-page: https://github.com/pmelchior/proxmin
Author: Peter Melchior, Fred Moolekamp
Author-email: peter.m.melchior@gmail.com
License: MIT
Keywords: optimization,constrained optimization,proximal algorithms,data analysis,non-negative matrix factorization
Platform: UNKNOWN
Classifier: Development Status :: 5 - Production/Stable
Classifier: License :: OSI Approved :: MIT License
Classifier: Intended Audience :: Developers
Classifier: Intended Audience :: Science/Research
Classifier: Operating System :: OS Independent
Classifier: Programming Language :: Python
Classifier: Topic :: Scientific/Engineering :: Information Analysis
Requires-Dist: numpy
Requires-Dist: scipy
